marketplace_standard_app_api/__init__.py
marketplace_standard_app_api/__main__.py
marketplace_standard_app_api/main.py
marketplace_standard_app_api/security.py
marketplace_standard_app_api/version.py
marketplace_standard_app_api/models/__init__.py
marketplace_standard_app_api/models/message_broker.py
marketplace_standard_app_api/models/object_storage.py
marketplace_standard_app_api/models/system.py
marketplace_standard_app_api/models/transformation.py
marketplace_standard_app_api/routers/__init__.py
marketplace_standard_app_api/routers/frontend.py
marketplace_standard_app_api/routers/object_storage.py
marketplace_standard_app_api/routers/system.py
marketplace_standard_app_api/routers/transformation.py
marketplace_standard_app_api-0.5.0.dist-info/entry_points.txt
marketplace_standard_app_api-0.5.0.dist-info/LICENSE
marketplace_standard_app_api-0.5.0.dist-info/WHEEL
marketplace_standard_app_api-0.5.0.dist-info/METADATA
marketplace_standard_app_api-0.5.0.dist-info/RECORD
