Metadata-Version: 2.1
Name: marketplace-standard-app-api
Version: 0.5.0
Summary: Materials-MarketPlace Standard App API
Author-email: Carl Simon Adorf et al <simon.adorf@epfl.ch>
Requires-Python: >=3.8,<4
Classifier: License :: OSI Approved :: MIT License
Requires-Dist: email-validator<=2.0, >=1.2.1
Requires-Dist: fastapi<=0.95.1, >0.75
Requires-Dist: python-multipart<=0.1, >0.0.5
Requires-Dist: requests<3.0, >2.26.0
Requires-Dist: click==8.1.3 ; extra == "cli"
Requires-Dist: bumpver==2021.1114 ; extra == "dev"
Requires-Dist: pytest==7.1.2 ; extra == "tests"
Project-URL: Home, https://github.com/materials-marketplace/standard-app-api
Provides-Extra: cli
Provides-Extra: dev
Provides-Extra: tests
